easylatex2image/__init__.py
easylatex2image/core.py
easylatex2image-0.0.1.dist-info/LICENSE
easylatex2image-0.0.1.dist-info/METADATA
easylatex2image-0.0.1.dist-info/WHEEL
easylatex2image-0.0.1.dist-info/top_level.txt
easylatex2image-0.0.1.dist-info/RECORD
