Metadata-Version: 2.1
Name: easylatex2image
Version: 0.0.1
Summary: another latex converter 2 pictures
Home-page: https://github.com/martinpflaum/easylatex2image
Author: Martin Pflaum
Author-email: martin.pflaum.09.03.1999@gmail.com
License: UNKNOWN
Project-URL: Bug Tracker, https://github.com/martinpflaum/easylatex2image/issues
Keywords: python,latex,image,png,jpg
Platform: UNKNOWN
Classifier: Programming Language :: Python :: 3
Classifier: License :: OSI Approved :: MIT License
Classifier: Operating System :: OS Independent
Requires-Python: >=3.6
Requires-Dist: pdf2image
